README.rst
setup.py
doubleclick/__init__.py
doubleclick.egg-info/PKG-INFO
doubleclick.egg-info/SOURCES.txt
doubleclick.egg-info/dependency_links.txt
doubleclick.egg-info/top_level.txt