Metadata-Version: 1.1
Name: doubleclick
Version: 0.1
Summary: Small collection of helper tools for command line applications
Home-page: https://github.com/mbr/doubleclick
Author: Marc Brinkmann
Author-email: git@marcbrinkmann.de
License: MIT
Platform: UNKNOWN
Classifier: Programming Language :: Python :: 3
